eutil/__init__.py
eutil/predicate.py
eutil/search.py
eutil/datastructures/__init__.py
eutil/datastructures/common.py
eutil/datastructures/lists.py
eutil/datastructures/trees/__init__.py
eutil/datastructures/trees/common.py
eutil-0.0.9.dist-info/METADATA
eutil-0.0.9.dist-info/WHEEL
eutil-0.0.9.dist-info/licenses/LICENSE
eutil-0.0.9.dist-info/RECORD
